{
  "country": "Italy",
  "region": "Sardegna",
  "province": "Nuoro",
  "crag": "Ulassai",
  "sector": "Lecorci",
  "routes": [
    { "name": "Panta rei", "grade": "7a" },
    { "name": "Astragalo", "grade": "7a+" },
    { "name": "Boomerang", "grade": "7c" },
    { "name": "Ubi maior", "grade": "8a+" },
    { "name": "The watchtower L1", "grade": null },
    { "name": "All along the watchtower L1+L2", "grade": null },
    { "name": "Hard Bitch", "grade": null },
    { "name": "Rafiki L1", "grade": "7a" },
    { "name": "Rafiki ext L1+L2", "grade": "7c" },
    { "name": "Minor cessat", "grade": "7b+" },
    { "name": "Coming back", "grade": "7a+" },
    { "name": "Stay away", "grade": null },
    { "name": "Kaftrio", "grade": "8a" },
    { "name": "Tito", "grade": "7a+" },
    { "name": "Alfa", "grade": "7b+" },
    { "name": "Drago nero", "grade": null },
    { "name": "Rurp", "grade": "6c" },
    { "name": "Mira il dito", "grade": "7c+" },
    { "name": "Doomsday", "grade": null },
    { "name": "Doomsday è bella così L1+L2", "grade": null },
    { "name": "Bella così", "grade": "7a+" },
    { "name": "Bellissima così L1+L2", "grade": "7c" },
    { "name": "Apparenza", "grade": "7b+" },
    { "name": "Dieta ferrea", "grade": "6b" },
    { "name": "Protuberanza equina", "grade": "6b+" },
    { "name": "Regime alimentare", "grade": "6a" },
    { "name": "Spina", "grade": "6a+" },
    { "name": "Bobolone", "grade": "6c" },
    { "name": "Chichino", "grade": "7a" },
    { "name": "Buchi buchi", "grade": "7b" },
    { "name": "Senza nome", "grade": null },
    { "name": "Lisio", "grade": "6b+" },
    { "name": "Frigo", "grade": "6c" },
    { "name": "Gino", "grade": "7b+" },
    { "name": "Pino", "grade": "7c" },
    { "name": "Nino", "grade": null },
    { "name": "Fammi vedere le tette", "grade": "5c" },
    { "name": "Spaghetti al rovo", "grade": "6b+" },
    { "name": "Stanza", "grade": "6b+" },
    { "name": "Atti di clemenza", "grade": "7a+" },
    { "name": "Zuccherino", "grade": "7a+" },
    { "name": "Tap", "grade": "7a" },
    { "name": "Tip L1", "grade": "6b+" },
    { "name": "A'bombazza L2", "grade": null },
    { "name": "Esagerato", "grade": "6a" },
    { "name": "MCB L1", "grade": "5c" },
    { "name": "TVB L1+L2", "grade": "6c+" },
    { "name": "MDF L1+L2", "grade": "7a" },
    { "name": "Pipo", "grade": "5a" },
    { "name": "Liz", "grade": "8a" },
    { "name": "Mezzo tiro", "grade": "6b+" },
    { "name": "La mano bianca", "grade": "8b" },
    { "name": "The laughing heart", "grade": "8c+" },
    { "name": "Aiutante", "grade": "6b" },
    { "name": "Pugnali volanti", "grade": "8b+" },
    { "name": "Vulcano", "grade": null },
    { "name": "Canna cinese", "grade": "8a" },
    { "name": "Dolce banana", "grade": "8b" },
    { "name": "Dimenticanze", "grade": "6c" },
    { "name": "Block", "grade": "7b" },
    { "name": "Spakka", "grade": "7c" },
    { "name": "Showroom dummies", "grade": "7c" },
    { "name": "Croce e delizia", "grade": "8a" },
    { "name": "P.T.", "grade": "7c" },
    { "name": "Ghost writer", "grade": "7c+" },
    { "name": "La trama del tempo L1", "grade": "7a+" },
    { "name": "La trama del tempo L1+L2", "grade": null },
    { "name": "Red cut", "grade": "7c" },
    { "name": "Bricolage", "grade": "7a" },
    { "name": "Tentazioni", "grade": "7a" },
    { "name": "Sinto", "grade": "7a" },
    { "name": "Finto", "grade": "7a+" },
    { "name": "Pinto", "grade": "7b" },
    { "name": "Rovo di bosco", "grade": "7a+" },
    { "name": "Kill Bill", "grade": null },
    { "name": "Sorgente", "grade": "7a" },
    { "name": "Gocce di memoria", "grade": "7a+" },
    { "name": "Indomabile", "grade": "7b" },
    { "name": "Grillo sacente", "grade": "7b" },
    { "name": "Mo...viola", "grade": null },
    { "name": "Movimenti socratici", "grade": "7a+" },
    { "name": "Umori al vespero", "grade": "7a+" },
    { "name": "Short and nameless", "grade": "7a+" },
    { "name": "Sottobosco", "grade": "6b" }
  ]
}
